jupyter_kernel_client/__init__.py
jupyter_kernel_client/_version.py
jupyter_kernel_client/client.py
jupyter_kernel_client/constants.py
jupyter_kernel_client/konsoleapp.py
jupyter_kernel_client/log.py
jupyter_kernel_client/manager.py
jupyter_kernel_client/models.py
jupyter_kernel_client/shell.py
jupyter_kernel_client/snippets.py
jupyter_kernel_client/utils.py
jupyter_kernel_client/wsclient.py
jupyter_kernel_client/tests/__init__.py
jupyter_kernel_client/tests/conftest.py
jupyter_kernel_client/tests/test_client.py
jupyter_kernel_client-0.8.0.dist-info/METADATA
jupyter_kernel_client-0.8.0.dist-info/WHEEL
jupyter_kernel_client-0.8.0.dist-info/entry_points.txt
jupyter_kernel_client-0.8.0.dist-info/licenses/LICENSE
jupyter_kernel_client-0.8.0.dist-info/RECORD
