Metadata-Version: 2.4
Name: jupyter_kernel_client
Version: 0.8.0
Project-URL: Home, https://github.com/datalayer/jupyter-kernel-client
Author-email: Datalayer <info@datalayer.io>
License: BSD 3-Clause License
License-File: LICENSE
Keywords: Jupyter
Classifier: Framework :: Jupyter
Classifier: Intended Audience :: Developers
Classifier: Intended Audience :: System Administrators
Classifier: License :: OSI Approved :: BSD License
Classifier: Programming Language :: Python
Classifier: Programming Language :: Python :: 3
Requires-Python: >=3.9
Requires-Dist: jupyter-client>=8.6.3
Requires-Dist: jupyter-core
Requires-Dist: jupyter-mimetypes
Requires-Dist: requests
Requires-Dist: traitlets>=5.3
Requires-Dist: typing-extensions
Requires-Dist: websocket-client
Provides-Extra: konsole
Requires-Dist: jupyter-console; extra == 'konsole'
Provides-Extra: lint
Requires-Dist: mdformat-gfm>=0.3.5; extra == 'lint'
Requires-Dist: mdformat>0.7; extra == 'lint'
Requires-Dist: pre-commit; extra == 'lint'
Requires-Dist: ruff; extra == 'lint'
Provides-Extra: test
Requires-Dist: ipykernel; extra == 'test'
Requires-Dist: jupyter-server<3,>=2.10; extra == 'test'
Requires-Dist: numpy; extra == 'test'
Requires-Dist: pandas; extra == 'test'
Requires-Dist: pytest-asyncio; extra == 'test'
Requires-Dist: pytest-cov; extra == 'test'
Requires-Dist: pytest-timeout; extra == 'test'
Requires-Dist: pytest>=7.0; extra == 'test'
Provides-Extra: typing
Requires-Dist: mypy>=0.990; extra == 'typing'
